llama_index/llms/nvidia_triton/__init__.py
llama_index/llms/nvidia_triton/base.py
llama_index/llms/nvidia_triton/utils.py
llama_index_llms_nvidia_triton-0.4.1.dist-info/METADATA
llama_index_llms_nvidia_triton-0.4.1.dist-info/WHEEL
llama_index_llms_nvidia_triton-0.4.1.dist-info/licenses/LICENSE
llama_index_llms_nvidia_triton-0.4.1.dist-info/RECORD
