Metadata-Version: 2.4
Name: llama-index-llms-nvidia-triton
Version: 0.4.1
Summary: llama-index llms nvidia triton integration
Author-email: Rohith Ramakrishnan <rrohith2001@gmail.com>
License-Expression: MIT
License-File: LICENSE
Requires-Python: <4.0,>=3.9
Requires-Dist: llama-index-core<0.15,>=0.13.0
Requires-Dist: tritonclient[grpc,http]<3,>=2.48.0
